nasspython/__init__.py
nasspython/__main__.py
nasspython/nass_api.py
nasspython-1.0.0.dist-info/LICENSE
nasspython-1.0.0.dist-info/METADATA
nasspython-1.0.0.dist-info/WHEEL
nasspython-1.0.0.dist-info/top_level.txt
nasspython-1.0.0.dist-info/RECORD
