Metadata-Version: 2.1
Name: nasspython
Version: 1.0.0
Summary: Wrapper for the NASS Quickstats database
Home-page: https://github.com/jackheinemann/nass_python
Author: Jack Heinemann
Author-email: jack@oenoke.com
License: MIT
Platform: UNKNOWN
Requires-Dist: requests
